LICENSE.txt
MANIFEST.in
README.rst
setup.py
doc/Makefile
doc/conf.py
doc/index.rst
doc/_build/html/_images/mfi_fragment_small.png
doc/_build/html/_static/comment-bright.png
doc/_build/html/_static/comment-close.png
doc/_build/html/_static/comment.png
doc/_build/html/_static/down-pressed.png
doc/_build/html/_static/down.png
doc/_build/html/_static/file.png
doc/_build/html/_static/minus.png
doc/_build/html/_static/plus.png
doc/_build/html/_static/up-pressed.png
doc/_build/html/_static/up.png
doc/development/authors.rst
doc/development/development.rst
doc/development/releases.rst
doc/reference/algo.rst
doc/reference/basic.rst
doc/reference/const.rst
doc/reference/data.rst
doc/reference/internals.rst
doc/reference/io.rst
doc/tutorial/applications.rst
doc/tutorial/cite.rst
doc/tutorial/examples.rst
doc/tutorial/graph.rst
doc/tutorial/install.rst
doc/tutorial/internal_coordinates.rst
doc/tutorial/mfi_fragment_small.png
doc/tutorial/molecule.rst
doc/tutorial/patterns.rst
doc/tutorial/units.rst
molmod/__init__.py
molmod/binning.py
molmod/bonds.py
molmod/clusters.py
molmod/common.c
molmod/common.h
molmod/constants.py
molmod/ext.pyx
molmod/ff.c
molmod/ff.h
molmod/ff.pxd
molmod/graphs.c
molmod/graphs.h
molmod/graphs.pxd
molmod/graphs.py
molmod/ic.py
molmod/isotopes.py
molmod/log.py
molmod/minimizer.py
molmod/molecular_graphs.py
molmod/molecules.c
molmod/molecules.h
molmod/molecules.pxd
molmod/molecules.py
molmod/pairff.py
molmod/periodic.py
molmod/quaternions.py
molmod/randomize.py
molmod/similarity.c
molmod/similarity.h
molmod/similarity.pxd
molmod/similarity.py
molmod/symmetry.py
molmod/toyff.py
molmod/transformations.py
molmod/unit_cells.c
molmod/unit_cells.h
molmod/unit_cells.pxd
molmod/unit_cells.py
molmod/units.py
molmod/utils.py
molmod/vectors.py
molmod/version.py
molmod/zmatrix.py
molmod.egg-info/PKG-INFO
molmod.egg-info/SOURCES.txt
molmod.egg-info/dependency_links.txt
molmod.egg-info/requires.txt
molmod.egg-info/top_level.txt
molmod/data/bonds.csv
molmod/data/bonds.ods
molmod/data/mass.mas03
molmod/data/nubtab03.asc
molmod/data/periodic.csv
molmod/data/periodic.ods
molmod/data/toyff_angles.txt
